odoo/addons/cms_delete_content_example/README.rst
odoo/addons/cms_delete_content_example/__init__.py
odoo/addons/cms_delete_content_example/__manifest__.py
odoo/addons/cms_delete_content_example/controllers/__init__.py
odoo/addons/cms_delete_content_example/controllers/main.py
odoo/addons/cms_delete_content_example/data/examples.xml
odoo/addons/cms_delete_content_example/data/ir.model.access.csv
odoo/addons/cms_delete_content_example/i18n/ca.po
odoo/addons/cms_delete_content_example/i18n/cms_delete_content_example.pot
odoo/addons/cms_delete_content_example/i18n/es.po
odoo/addons/cms_delete_content_example/models/__init__.py
odoo/addons/cms_delete_content_example/models/example.py
odoo/addons/cms_delete_content_example/static/description/icon.png
odoo/addons/cms_delete_content_example/templates/example.xml
odoo11_addon_cms_delete_content_example-11.0.1.0.0.99.dev6.dist-info/METADATA
odoo11_addon_cms_delete_content_example-11.0.1.0.0.99.dev6.dist-info/WHEEL
odoo11_addon_cms_delete_content_example-11.0.1.0.0.99.dev6.dist-info/top_level.txt
odoo11_addon_cms_delete_content_example-11.0.1.0.0.99.dev6.dist-info/RECORD
